oh_my_batch/__init__.py
oh_my_batch/__main__.py
oh_my_batch/assets/__init__.py
oh_my_batch/assets/functions.sh
oh_my_batch/batch.py
oh_my_batch/cli.py
oh_my_batch/combo.py
oh_my_batch/job.py
oh_my_batch/misc.py
oh_my_batch/util.py
oh_my_batch-0.6.2.dist-info/LICENSE
oh_my_batch-0.6.2.dist-info/METADATA
oh_my_batch-0.6.2.dist-info/WHEEL
oh_my_batch-0.6.2.dist-info/entry_points.txt
oh_my_batch-0.6.2.dist-info/RECORD
