Metadata-Version: 2.1
Name: oh-my-batch
Version: 0.6.2
Summary: 
License: GPL
Author: weihong.xu
Author-email: xuweihong.cn@gmail.com
Requires-Python: >=3.8,<4.0
Classifier: License :: Other/Proprietary License
Classifier: Programming Language :: Python :: 3
Classifier: Programming Language :: Python :: 3.8
Classifier: Programming Language :: Python :: 3.9
Classifier: Programming Language :: Python :: 3.10
Classifier: Programming Language :: Python :: 3.11
Classifier: Programming Language :: Python :: 3.12
Requires-Dist: fire (>=0.5.0,<0.6.0)
